mixpanel/__init__.py
mixpanel_py-4.0.3.dist-info/DESCRIPTION.rst
mixpanel_py-4.0.3.dist-info/METADATA
mixpanel_py-4.0.3.dist-info/metadata.json
mixpanel_py-4.0.3.dist-info/RECORD
mixpanel_py-4.0.3.dist-info/top_level.txt
mixpanel_py-4.0.3.dist-info/WHEEL
