Metadata-Version: 2.0
Name: mixpanel-py
Version: 4.0.3
Summary: Official Mixpanel library for Python
Home-page: https://github.com/mixpanel/mixpanel-python
Author: Mixpanel, Inc.
Author-email: dev@mixpanel.com
License: Apache
Keywords: mixpanel analytics
Platform: UNKNOWN
Classifier: License :: OSI Approved :: Apache Software License
Classifier: Operating System :: OS Independent
Classifier: Programming Language :: Python :: 2 :: Only
